scrapbook_cli-1.0.3.dist-info/licenses/LICENSE
src/scrapbook/main.py
scrapbook_cli-1.0.3.dist-info/METADATA
scrapbook_cli-1.0.3.dist-info/WHEEL
scrapbook_cli-1.0.3.dist-info/entry_points.txt
scrapbook_cli-1.0.3.dist-info/top_level.txt
scrapbook_cli-1.0.3.dist-info/RECORD
