Metadata-Version: 2.4
Name: scrapbook-cli
Version: 1.0.3
Summary: Logging and journaling from the terminal
Author-email: velvetSymphony <abhishek@achandrasekar.com>
License: GPL-3.0-or-later
Requires-Python: >=3.9.0
License-File: LICENSE
Requires-Dist: PyYAML==6.0.2
Dynamic: license-file
